{
	"components": {
		"examples": {},
		"headers": {},
		"parameters": {},
		"requestBodies": {},
		"responses": {},
		"schemas": {
			"PingResponse": {
				"properties": {
					"message": {
						"type": "string"
					}
				},
				"required": [
					"message"
				],
				"type": "object",
				"additionalProperties": false
			},
			"User": {
				"properties": {
					"id": {
						"type": "number",
						"format": "double"
					},
					"firstName": {
						"type": "string"
					},
					"lastName": {
						"type": "string"
					},
					"email": {
						"type": "string"
					},
					"password": {
						"type": "string"
					},
					"posts": {
						"items": {
							"$ref": "#/components/schemas/Post"
						},
						"type": "array"
					},
					"comments": {
						"items": {
							"$ref": "#/components/schemas/Comment"
						},
						"type": "array"
					},
					"createdAt": {
						"type": "string",
						"format": "date-time"
					},
					"updatedAt": {
						"type": "string",
						"format": "date-time"
					}
				},
				"required": [
					"id",
					"firstName",
					"lastName",
					"email",
					"password",
					"posts",
					"comments",
					"createdAt",
					"updatedAt"
				],
				"type": "object",
				"additionalProperties": false
			},
			"Post": {
				"properties": {
					"id": {
						"type": "number",
						"format": "double"
					},
					"title": {
						"type": "string"
					},
					"content": {
						"type": "string"
					},
					"userId": {
						"type": "number",
						"format": "double"
					},
					"user": {
						"$ref": "#/components/schemas/User"
					},
					"comments": {
						"items": {
							"$ref": "#/components/schemas/Comment"
						},
						"type": "array"
					},
					"createdAt": {
						"type": "string",
						"format": "date-time"
					},
					"updatedAt": {
						"type": "string",
						"format": "date-time"
					},
					"message": {
						"type": "string"
					}
				},
				"required": [
					"id",
					"title",
					"content",
					"userId",
					"user",
					"comments",
					"createdAt",
					"updatedAt",
					"message"
				],
				"type": "object",
				"additionalProperties": false
			},
			"Comment": {
				"properties": {
					"id": {
						"type": "number",
						"format": "double"
					},
					"content": {
						"type": "string"
					},
					"userId": {
						"type": "number",
						"format": "double"
					},
					"user": {
						"$ref": "#/components/schemas/User"
					},
					"postId": {
						"type": "number",
						"format": "double"
					},
					"post": {
						"$ref": "#/components/schemas/Post"
					},
					"createdAt": {
						"type": "string",
						"format": "date-time"
					},
					"updatedAt": {
						"type": "string",
						"format": "date-time"
					},
					"message": {
						"type": "string"
					}
				},
				"required": [
					"id",
					"content",
					"userId",
					"user",
					"postId",
					"post",
					"createdAt",
					"updatedAt",
					"message"
				],
				"type": "object",
				"additionalProperties": false
			},
			"IAuthPayload": {
				"properties": {
					"firstName": {
						"type": "string"
					},
					"lastName": {
						"type": "string"
					},
					"email": {
						"type": "string"
					},
					"password": {
						"type": "string"
					}
				},
				"required": [
					"firstName",
					"lastName",
					"email",
					"password"
				],
				"type": "object",
				"additionalProperties": false
			},
			"OAuthPayload": {
				"properties": {
					"status": {
						"type": "string"
					},
					"result_code": {
						"type": "number",
						"format": "double"
					},
					"email": {
						"type": "string"
					},
					"token": {
						"type": "string"
					},
					"message": {
						"type": "string"
					}
				},
				"type": "object",
				"additionalProperties": false
			},
			"IUserPayload": {
				"properties": {
					"firstName": {
						"type": "string"
					},
					"lastName": {
						"type": "string"
					},
					"email": {
						"type": "string"
					},
					"password": {
						"type": "string"
					}
				},
				"required": [
					"firstName",
					"lastName",
					"email",
					"password"
				],
				"type": "object",
				"additionalProperties": false
			},
			"IPostPayload": {
				"properties": {
					"title": {
						"type": "string"
					},
					"content": {
						"type": "string"
					},
					"userId": {
						"type": "number",
						"format": "double"
					}
				},
				"required": [
					"title",
					"content",
					"userId"
				],
				"type": "object",
				"additionalProperties": false
			},
			"ICommentPayload": {
				"properties": {
					"content": {
						"type": "string"
					},
					"userId": {
						"type": "number",
						"format": "double"
					},
					"commentId": {
						"type": "number",
						"format": "double"
					}
				},
				"required": [
					"content",
					"userId",
					"commentId"
				],
				"type": "object",
				"additionalProperties": false
			},
			"Artist": {
				"properties": {
					"id": {
						"type": "number",
						"format": "double"
					},
					"name": {
						"type": "string"
					},
					"slug": {
						"type": "string"
					},
					"image": {
						"type": "string"
					},
					"albums": {
						"items": {
							"$ref": "#/components/schemas/Album"
						},
						"type": "array"
					},
					"tracks": {
						"items": {
							"$ref": "#/components/schemas/Track"
						},
						"type": "array"
					}
				},
				"required": [
					"id",
					"name",
					"slug",
					"image",
					"albums",
					"tracks"
				],
				"type": "object",
				"additionalProperties": false
			},
			"Album": {
				"properties": {
					"id": {
						"type": "number",
						"format": "double"
					},
					"title": {
						"type": "string"
					},
					"slug": {
						"type": "string"
					},
					"location": {
						"type": "string"
					},
					"views": {
						"type": "number",
						"format": "double"
					},
					"downloads": {
						"type": "number",
						"format": "double"
					},
					"release_date": {
						"type": "string",
						"format": "date-time"
					},
					"featured": {
						"type": "number",
						"format": "double"
					},
					"catalog": {
						"type": "string"
					},
					"top_album": {
						"type": "number",
						"format": "double"
					},
					"vinyl_album": {
						"type": "number",
						"format": "double"
					},
					"bandcamp_album": {
						"type": "number",
						"format": "double"
					},
					"artist": {
						"$ref": "#/components/schemas/Artist"
					},
					"category": {
						"$ref": "#/components/schemas/Category"
					},
					"publisher": {
						"$ref": "#/components/schemas/Publisher"
					},
					"language": {
						"$ref": "#/components/schemas/Language"
					},
					"tracks": {
						"items": {
							"$ref": "#/components/schemas/Track"
						},
						"type": "array"
					},
					"created_at": {
						"type": "string",
						"format": "date-time"
					},
					"updated_at": {
						"type": "string",
						"format": "date-time"
					},
					"message": {
						"type": "string"
					}
				},
				"required": [
					"id",
					"title",
					"slug",
					"location",
					"views",
					"downloads",
					"release_date",
					"featured",
					"catalog",
					"top_album",
					"vinyl_album",
					"bandcamp_album",
					"artist",
					"category",
					"publisher",
					"language",
					"tracks",
					"created_at",
					"updated_at",
					"message"
				],
				"type": "object",
				"additionalProperties": false
			},
			"Track": {
				"properties": {
					"id": {
						"type": "number",
						"format": "double"
					},
					"title": {
						"type": "string"
					},
					"slug": {
						"type": "string"
					},
					"location": {
						"type": "string"
					},
					"duration": {
						"type": "number",
						"format": "double"
					},
					"bpm": {
						"type": "number",
						"format": "double"
					},
					"remixed": {
						"type": "string"
					},
					"filesize": {
						"type": "number",
						"format": "double"
					},
					"downloads": {
						"type": "number",
						"format": "double"
					},
					"search": {
						"type": "string"
					},
					"artist": {
						"$ref": "#/components/schemas/Artist"
					},
					"key": {
						"$ref": "#/components/schemas/Key"
					},
					"category": {
						"$ref": "#/components/schemas/Category"
					},
					"album": {
						"$ref": "#/components/schemas/Album"
					},
					"created_at": {
						"type": "string",
						"format": "date-time"
					},
					"updated_at": {
						"type": "string",
						"format": "date-time"
					},
					"message": {
						"type": "string"
					}
				},
				"required": [
					"id",
					"title",
					"slug",
					"location",
					"duration",
					"bpm",
					"remixed",
					"filesize",
					"downloads",
					"search",
					"artist",
					"key",
					"category",
					"album",
					"created_at",
					"updated_at",
					"message"
				],
				"type": "object",
				"additionalProperties": false
			},
			"Key": {
				"properties": {
					"id": {
						"type": "number",
						"format": "double"
					},
					"name": {
						"type": "string"
					},
					"slug": {
						"type": "string"
					},
					"tracks": {
						"items": {
							"$ref": "#/components/schemas/Track"
						},
						"type": "array"
					}
				},
				"required": [
					"id",
					"name",
					"slug",
					"tracks"
				],
				"type": "object",
				"additionalProperties": false
			},
			"Category": {
				"properties": {
					"id": {
						"type": "number",
						"format": "double"
					},
					"name": {
						"type": "string"
					},
					"slug": {
						"type": "string"
					},
					"albums": {
						"items": {
							"$ref": "#/components/schemas/Album"
						},
						"type": "array"
					},
					"tracks": {
						"items": {
							"$ref": "#/components/schemas/Track"
						},
						"type": "array"
					}
				},
				"required": [
					"id",
					"name",
					"slug",
					"albums",
					"tracks"
				],
				"type": "object",
				"additionalProperties": false
			},
			"Publisher": {
				"properties": {
					"id": {
						"type": "number",
						"format": "double"
					},
					"name": {
						"type": "string"
					},
					"slug": {
						"type": "string"
					},
					"albums": {
						"items": {
							"$ref": "#/components/schemas/Album"
						},
						"type": "array"
					}
				},
				"required": [
					"id",
					"name",
					"slug",
					"albums"
				],
				"type": "object",
				"additionalProperties": false
			},
			"Language": {
				"properties": {
					"id": {
						"type": "number",
						"format": "double"
					},
					"name": {
						"type": "string"
					},
					"slug": {
						"type": "string"
					},
					"albums": {
						"items": {
							"$ref": "#/components/schemas/Album"
						},
						"type": "array"
					}
				},
				"required": [
					"id",
					"name",
					"slug",
					"albums"
				],
				"type": "object",
				"additionalProperties": false
			},
			"IArtistPayload": {
				"properties": {
					"name": {
						"type": "string"
					},
					"slug": {
						"type": "string"
					}
				},
				"required": [
					"name",
					"slug"
				],
				"type": "object",
				"additionalProperties": false
			},
			"IAlbumPayload": {
				"properties": {
					"title": {
						"type": "string"
					},
					"slug": {
						"type": "string"
					},
					"artist_id": {
						"type": "number",
						"format": "double"
					}
				},
				"required": [
					"title",
					"slug",
					"artist_id"
				],
				"type": "object",
				"additionalProperties": false
			},
			"ICategoryPayload": {
				"properties": {
					"name": {
						"type": "string"
					},
					"slug": {
						"type": "string"
					}
				},
				"required": [
					"name",
					"slug"
				],
				"type": "object",
				"additionalProperties": false
			},
			"IUploadBulkPayload": {
				"properties": {
					"uploadpath": {
						"type": "string"
					}
				},
				"required": [
					"uploadpath"
				],
				"type": "object",
				"additionalProperties": false
			},
			"ITrackPayload": {
				"properties": {
					"title": {
						"type": "string"
					},
					"slug": {
						"type": "string"
					}
				},
				"required": [
					"title",
					"slug"
				],
				"type": "object",
				"additionalProperties": false
			},
			"IKeyPayload": {
				"properties": {
					"name": {
						"type": "string"
					},
					"slug": {
						"type": "string"
					}
				},
				"required": [
					"name",
					"slug"
				],
				"type": "object",
				"additionalProperties": false
			}
		},
		"securitySchemes": {}
	},
	"info": {
		"title": "express-typescript",
		"version": "1.0.0",
		"license": {
			"name": "ISC"
		},
		"contact": {}
	},
	"openapi": "3.0.0",
	"paths": {
		"/api/v1/ping": {
			"get": {
				"operationId": "GetMessage",
				"responses": {
					"200": {
						"description": "Ok",
						"content": {
							"application/json": {
								"schema": {
									"$ref": "#/components/schemas/PingResponse"
								}
							}
						}
					}
				},
				"security": [],
				"parameters": []
			}
		},
		"/api/v1/auth/signup": {
			"post": {
				"operationId": "SignUpUser",
				"responses": {
					"200": {
						"description": "Ok",
						"content": {
							"application/json": {
								"schema": {
									"$ref": "#/components/schemas/User"
								}
							}
						}
					}
				},
				"tags": [
					"Auth"
				],
				"security": [],
				"parameters": [],
				"requestBody": {
					"required": true,
					"content": {
						"application/json": {
							"schema": {
								"$ref": "#/components/schemas/IAuthPayload"
							}
						}
					}
				}
			}
		},
		"/api/v1/auth/signin": {
			"post": {
				"operationId": "SignInUser",
				"responses": {
					"200": {
						"description": "Ok",
						"content": {
							"application/json": {
								"schema": {
									"allOf": [
										{
											"$ref": "#/components/schemas/OAuthPayload"
										}
									],
									"nullable": true
								}
							}
						}
					}
				},
				"tags": [
					"Auth"
				],
				"security": [],
				"parameters": [],
				"requestBody": {
					"required": true,
					"content": {
						"application/json": {
							"schema": {
								"$ref": "#/components/schemas/IAuthPayload"
							}
						}
					}
				}
			}
		},
		"/api/v1/users": {
			"get": {
				"operationId": "GetUsers",
				"responses": {
					"200": {
						"description": "Ok",
						"content": {
							"application/json": {
								"schema": {
									"items": {
										"$ref": "#/components/schemas/User"
									},
									"type": "array"
								}
							}
						}
					}
				},
				"tags": [
					"User"
				],
				"security": [
					{
						"jwt": []
					}
				],
				"parameters": []
			},
			"post": {
				"operationId": "CreateUser",
				"responses": {
					"200": {
						"description": "Ok",
						"content": {
							"application/json": {
								"schema": {
									"$ref": "#/components/schemas/User"
								}
							}
						}
					}
				},
				"tags": [
					"User"
				],
				"security": [
					{
						"jwt": []
					}
				],
				"parameters": [],
				"requestBody": {
					"required": true,
					"content": {
						"application/json": {
							"schema": {
								"$ref": "#/components/schemas/IUserPayload"
							}
						}
					}
				}
			}
		},
		"/api/v1/users/{id}": {
			"get": {
				"operationId": "GetUser",
				"responses": {
					"200": {
						"description": "Ok",
						"content": {
							"application/json": {
								"schema": {
									"allOf": [
										{
											"$ref": "#/components/schemas/User"
										}
									],
									"nullable": true
								}
							}
						}
					}
				},
				"tags": [
					"User"
				],
				"security": [
					{
						"jwt": []
					}
				],
				"parameters": [
					{
						"in": "path",
						"name": "id",
						"required": true,
						"schema": {
							"type": "string"
						}
					}
				]
			},
			"put": {
				"operationId": "UpdateUser",
				"responses": {
					"200": {
						"description": "Ok",
						"content": {
							"application/json": {
								"schema": {
									"allOf": [
										{
											"$ref": "#/components/schemas/User"
										}
									],
									"nullable": true
								}
							}
						}
					}
				},
				"tags": [
					"User"
				],
				"security": [
					{
						"jwt": []
					}
				],
				"parameters": [
					{
						"in": "path",
						"name": "id",
						"required": true,
						"schema": {
							"type": "string"
						}
					}
				],
				"requestBody": {
					"required": true,
					"content": {
						"application/json": {
							"schema": {
								"$ref": "#/components/schemas/IUserPayload"
							}
						}
					}
				}
			},
			"delete": {
				"operationId": "DeleteUser",
				"responses": {
					"200": {
						"description": "Ok",
						"content": {
							"application/json": {
								"schema": {
									"allOf": [
										{
											"$ref": "#/components/schemas/User"
										}
									],
									"nullable": true
								}
							}
						}
					}
				},
				"tags": [
					"User"
				],
				"security": [
					{
						"jwt": []
					}
				],
				"parameters": [
					{
						"in": "path",
						"name": "id",
						"required": true,
						"schema": {
							"type": "string"
						}
					}
				]
			}
		},
		"/api/v1/posts": {
			"get": {
				"operationId": "GetPosts",
				"responses": {
					"200": {
						"description": "Ok",
						"content": {
							"application/json": {
								"schema": {
									"items": {
										"$ref": "#/components/schemas/Post"
									},
									"type": "array"
								}
							}
						}
					}
				},
				"tags": [
					"Post"
				],
				"security": [
					{
						"jwt": []
					}
				],
				"parameters": []
			}
		},
		"/api/v1/posts/{id}": {
			"get": {
				"operationId": "GetPost",
				"responses": {
					"200": {
						"description": "Ok",
						"content": {
							"application/json": {
								"schema": {
									"allOf": [
										{
											"$ref": "#/components/schemas/Post"
										}
									],
									"nullable": true
								}
							}
						}
					}
				},
				"tags": [
					"Post"
				],
				"security": [
					{
						"jwt": []
					}
				],
				"parameters": [
					{
						"in": "path",
						"name": "id",
						"required": true,
						"schema": {
							"type": "string"
						}
					}
				]
			},
			"put": {
				"operationId": "UpdatePost",
				"responses": {
					"200": {
						"description": "Ok",
						"content": {
							"application/json": {
								"schema": {
									"allOf": [
										{
											"$ref": "#/components/schemas/Post"
										}
									],
									"nullable": true
								}
							}
						}
					}
				},
				"tags": [
					"Post"
				],
				"security": [
					{
						"jwt": []
					}
				],
				"parameters": [
					{
						"in": "path",
						"name": "id",
						"required": true,
						"schema": {
							"type": "string"
						}
					}
				],
				"requestBody": {
					"required": true,
					"content": {
						"application/json": {
							"schema": {
								"$ref": "#/components/schemas/IPostPayload"
							}
						}
					}
				}
			},
			"delete": {
				"operationId": "DeletePost",
				"responses": {
					"200": {
						"description": "Ok",
						"content": {
							"application/json": {
								"schema": {
									"allOf": [
										{
											"$ref": "#/components/schemas/Post"
										}
									],
									"nullable": true
								}
							}
						}
					}
				},
				"tags": [
					"Post"
				],
				"security": [
					{
						"jwt": []
					}
				],
				"parameters": [
					{
						"in": "path",
						"name": "id",
						"required": true,
						"schema": {
							"type": "string"
						}
					}
				]
			}
		},
		"/api/v1/comments": {
			"get": {
				"operationId": "GetComments",
				"responses": {
					"200": {
						"description": "Ok",
						"content": {
							"application/json": {
								"schema": {
									"items": {
										"$ref": "#/components/schemas/Comment"
									},
									"type": "array"
								}
							}
						}
					}
				},
				"tags": [
					"Comment"
				],
				"security": [
					{
						"jwt": []
					}
				],
				"parameters": []
			},
			"post": {
				"operationId": "CreateComment",
				"responses": {
					"200": {
						"description": "Ok",
						"content": {
							"application/json": {
								"schema": {
									"$ref": "#/components/schemas/Comment"
								}
							}
						}
					}
				},
				"tags": [
					"Comment"
				],
				"security": [
					{
						"jwt": []
					}
				],
				"parameters": [],
				"requestBody": {
					"required": true,
					"content": {
						"application/json": {
							"schema": {
								"$ref": "#/components/schemas/ICommentPayload"
							}
						}
					}
				}
			}
		},
		"/api/v1/comments/{id}": {
			"get": {
				"operationId": "GetComment",
				"responses": {
					"200": {
						"description": "Ok",
						"content": {
							"application/json": {
								"schema": {
									"allOf": [
										{
											"$ref": "#/components/schemas/Comment"
										}
									],
									"nullable": true
								}
							}
						}
					}
				},
				"tags": [
					"Comment"
				],
				"security": [
					{
						"jwt": []
					}
				],
				"parameters": [
					{
						"in": "path",
						"name": "id",
						"required": true,
						"schema": {
							"type": "string"
						}
					}
				]
			},
			"put": {
				"operationId": "UpdateComment",
				"responses": {
					"200": {
						"description": "Ok",
						"content": {
							"application/json": {
								"schema": {
									"allOf": [
										{
											"$ref": "#/components/schemas/Comment"
										}
									],
									"nullable": true
								}
							}
						}
					}
				},
				"tags": [
					"Comment"
				],
				"security": [
					{
						"jwt": []
					}
				],
				"parameters": [
					{
						"in": "path",
						"name": "id",
						"required": true,
						"schema": {
							"type": "string"
						}
					}
				],
				"requestBody": {
					"required": true,
					"content": {
						"application/json": {
							"schema": {
								"$ref": "#/components/schemas/ICommentPayload"
							}
						}
					}
				}
			},
			"delete": {
				"operationId": "DeleteComment",
				"responses": {
					"200": {
						"description": "Ok",
						"content": {
							"application/json": {
								"schema": {
									"allOf": [
										{
											"$ref": "#/components/schemas/Comment"
										}
									],
									"nullable": true
								}
							}
						}
					}
				},
				"tags": [
					"Comment"
				],
				"security": [
					{
						"jwt": []
					}
				],
				"parameters": [
					{
						"in": "path",
						"name": "id",
						"required": true,
						"schema": {
							"type": "string"
						}
					}
				]
			}
		},
		"/api/v1/artists": {
			"get": {
				"operationId": "GetArtists",
				"responses": {
					"200": {
						"description": "Ok",
						"content": {
							"application/json": {
								"schema": {
									"items": {
										"$ref": "#/components/schemas/Artist"
									},
									"type": "array"
								}
							}
						}
					}
				},
				"tags": [
					"Artist"
				],
				"security": [
					{
						"jwt": []
					}
				],
				"parameters": []
			},
			"post": {
				"operationId": "CreateArtist",
				"responses": {
					"200": {
						"description": "Ok",
						"content": {
							"application/json": {
								"schema": {
									"$ref": "#/components/schemas/Artist"
								}
							}
						}
					}
				},
				"tags": [
					"Artist"
				],
				"security": [
					{
						"jwt": []
					}
				],
				"parameters": [],
				"requestBody": {
					"required": true,
					"content": {
						"application/json": {
							"schema": {
								"$ref": "#/components/schemas/IArtistPayload"
							}
						}
					}
				}
			}
		},
		"/api/v1/artists/{id}": {
			"get": {
				"operationId": "GetArtist",
				"responses": {
					"200": {
						"description": "Ok",
						"content": {
							"application/json": {
								"schema": {
									"allOf": [
										{
											"$ref": "#/components/schemas/Artist"
										}
									],
									"nullable": true
								}
							}
						}
					}
				},
				"tags": [
					"Artist"
				],
				"security": [
					{
						"jwt": []
					}
				],
				"parameters": [
					{
						"in": "path",
						"name": "id",
						"required": true,
						"schema": {
							"type": "string"
						}
					}
				]
			},
			"put": {
				"operationId": "UpdateArtist",
				"responses": {
					"200": {
						"description": "Ok",
						"content": {
							"application/json": {
								"schema": {
									"allOf": [
										{
											"$ref": "#/components/schemas/Artist"
										}
									],
									"nullable": true
								}
							}
						}
					}
				},
				"tags": [
					"Artist"
				],
				"security": [
					{
						"jwt": []
					}
				],
				"parameters": [
					{
						"in": "path",
						"name": "id",
						"required": true,
						"schema": {
							"type": "string"
						}
					}
				],
				"requestBody": {
					"required": true,
					"content": {
						"application/json": {
							"schema": {
								"$ref": "#/components/schemas/IArtistPayload"
							}
						}
					}
				}
			},
			"delete": {
				"operationId": "DeleteArtist",
				"responses": {
					"200": {
						"description": "Ok",
						"content": {
							"application/json": {
								"schema": {
									"allOf": [
										{
											"$ref": "#/components/schemas/Artist"
										}
									],
									"nullable": true
								}
							}
						}
					}
				},
				"tags": [
					"Artist"
				],
				"security": [
					{
						"jwt": []
					}
				],
				"parameters": [
					{
						"in": "path",
						"name": "id",
						"required": true,
						"schema": {
							"type": "string"
						}
					}
				]
			}
		},
		"/api/v1/albums": {
			"get": {
				"operationId": "GetAlbums",
				"responses": {
					"200": {
						"description": "Ok",
						"content": {
							"application/json": {
								"schema": {
									"items": {
										"$ref": "#/components/schemas/Album"
									},
									"type": "array"
								}
							}
						}
					}
				},
				"tags": [
					"Album"
				],
				"security": [],
				"parameters": [
					{
						"in": "query",
						"name": "skip",
						"required": true,
						"schema": {
							"type": "string"
						}
					},
					{
						"in": "query",
						"name": "limit",
						"required": true,
						"schema": {
							"type": "string"
						}
					},
					{
						"in": "query",
						"name": "publisher",
						"required": true,
						"schema": {
							"type": "string"
						}
					}
				]
			}
		},
		"/api/v1/albums/featured-albums": {
			"get": {
				"operationId": "GetFeaturedAlbums",
				"responses": {
					"200": {
						"description": "Ok",
						"content": {
							"application/json": {
								"schema": {
									"items": {
										"$ref": "#/components/schemas/Album"
									},
									"type": "array"
								}
							}
						}
					}
				},
				"tags": [
					"Album"
				],
				"security": [],
				"parameters": []
			}
		},
		"/api/v1/albums/top-albums": {
			"get": {
				"operationId": "GetTopAlbums",
				"responses": {
					"200": {
						"description": "Ok",
						"content": {
							"application/json": {
								"schema": {
									"items": {
										"$ref": "#/components/schemas/Album"
									},
									"type": "array"
								}
							}
						}
					}
				},
				"tags": [
					"Album"
				],
				"security": [],
				"parameters": []
			}
		},
		"/api/v1/albums/vinyl-albums": {
			"get": {
				"operationId": "GetVinylAlbums",
				"responses": {
					"200": {
						"description": "Ok",
						"content": {
							"application/json": {
								"schema": {
									"items": {
										"$ref": "#/components/schemas/Album"
									},
									"type": "array"
								}
							}
						}
					}
				},
				"tags": [
					"Album"
				],
				"security": [],
				"parameters": []
			}
		},
		"/api/v1/albums/bandcamp-albums": {
			"get": {
				"operationId": "GetBandcampAlbums",
				"responses": {
					"200": {
						"description": "Ok",
						"content": {
							"application/json": {
								"schema": {
									"items": {
										"$ref": "#/components/schemas/Album"
									},
									"type": "array"
								}
							}
						}
					}
				},
				"tags": [
					"Album"
				],
				"security": [],
				"parameters": []
			}
		},
		"/api/v1/albums/picked-albums": {
			"get": {
				"operationId": "GetPickedAlbums",
				"responses": {
					"200": {
						"description": "Ok",
						"content": {
							"application/json": {
								"schema": {
									"items": {
										"$ref": "#/components/schemas/Album"
									},
									"type": "array"
								}
							}
						}
					}
				},
				"tags": [
					"Album"
				],
				"security": [],
				"parameters": [
					{
						"in": "query",
						"name": "type",
						"required": true,
						"schema": {
							"type": "string"
						}
					},
					{
						"in": "query",
						"name": "skip",
						"required": true,
						"schema": {
							"type": "string"
						}
					},
					{
						"in": "query",
						"name": "limit",
						"required": true,
						"schema": {
							"type": "string"
						}
					},
					{
						"in": "query",
						"name": "publisher",
						"required": true,
						"schema": {
							"type": "string"
						}
					}
				]
			}
		},
		"/api/v1/albums/genre-albums/{slug}": {
			"get": {
				"operationId": "GetGenreAlbums",
				"responses": {
					"200": {
						"description": "Ok",
						"content": {
							"application/json": {
								"schema": {
									"items": {
										"$ref": "#/components/schemas/Album"
									},
									"type": "array"
								}
							}
						}
					}
				},
				"tags": [
					"Album"
				],
				"security": [],
				"parameters": [
					{
						"in": "path",
						"name": "slug",
						"required": true,
						"schema": {
							"type": "string"
						}
					},
					{
						"in": "query",
						"name": "skip",
						"required": true,
						"schema": {
							"type": "string"
						}
					},
					{
						"in": "query",
						"name": "limit",
						"required": true,
						"schema": {
							"type": "string"
						}
					}
				]
			}
		},
		"/api/v1/albums/{slug}": {
			"get": {
				"operationId": "GetOneAlbum",
				"responses": {
					"200": {
						"description": "Ok",
						"content": {
							"application/json": {
								"schema": {
									"allOf": [
										{
											"$ref": "#/components/schemas/Album"
										}
									],
									"nullable": true
								}
							}
						}
					}
				},
				"tags": [
					"Album"
				],
				"security": [],
				"parameters": [
					{
						"in": "path",
						"name": "slug",
						"required": true,
						"schema": {
							"type": "string"
						}
					}
				]
			}
		},
		"/api/v1/albums/{id}": {
			"put": {
				"operationId": "UpdateAlbum",
				"responses": {
					"200": {
						"description": "Ok",
						"content": {
							"application/json": {
								"schema": {
									"allOf": [
										{
											"$ref": "#/components/schemas/Album"
										}
									],
									"nullable": true
								}
							}
						}
					}
				},
				"tags": [
					"Album"
				],
				"security": [],
				"parameters": [
					{
						"in": "path",
						"name": "id",
						"required": true,
						"schema": {
							"type": "string"
						}
					}
				],
				"requestBody": {
					"required": true,
					"content": {
						"application/json": {
							"schema": {
								"$ref": "#/components/schemas/IAlbumPayload"
							}
						}
					}
				}
			},
			"delete": {
				"operationId": "DeleteAlbum",
				"responses": {
					"200": {
						"description": "Ok",
						"content": {
							"application/json": {
								"schema": {
									"allOf": [
										{
											"$ref": "#/components/schemas/Album"
										}
									],
									"nullable": true
								}
							}
						}
					}
				},
				"tags": [
					"Album"
				],
				"security": [],
				"parameters": [
					{
						"in": "path",
						"name": "id",
						"required": true,
						"schema": {
							"type": "string"
						}
					}
				]
			}
		},
		"/api/v1/categories": {
			"get": {
				"operationId": "GetCategories",
				"responses": {
					"200": {
						"description": "Ok",
						"content": {
							"application/json": {
								"schema": {
									"items": {
										"$ref": "#/components/schemas/Category"
									},
									"type": "array"
								}
							}
						}
					}
				},
				"tags": [
					"Category"
				],
				"security": [
					{
						"jwt": []
					}
				],
				"parameters": []
			},
			"post": {
				"operationId": "CreateCategory",
				"responses": {
					"200": {
						"description": "Ok",
						"content": {
							"application/json": {
								"schema": {
									"$ref": "#/components/schemas/Category"
								}
							}
						}
					}
				},
				"tags": [
					"Category"
				],
				"security": [
					{
						"jwt": []
					}
				],
				"parameters": [],
				"requestBody": {
					"required": true,
					"content": {
						"application/json": {
							"schema": {
								"$ref": "#/components/schemas/ICategoryPayload"
							}
						}
					}
				}
			}
		},
		"/api/v1/categories/{id}": {
			"get": {
				"operationId": "GetCategory",
				"responses": {
					"200": {
						"description": "Ok",
						"content": {
							"application/json": {
								"schema": {
									"allOf": [
										{
											"$ref": "#/components/schemas/Category"
										}
									],
									"nullable": true
								}
							}
						}
					}
				},
				"tags": [
					"Category"
				],
				"security": [
					{
						"jwt": []
					}
				],
				"parameters": [
					{
						"in": "path",
						"name": "id",
						"required": true,
						"schema": {
							"type": "string"
						}
					}
				]
			},
			"put": {
				"operationId": "UpdateCategory",
				"responses": {
					"200": {
						"description": "Ok",
						"content": {
							"application/json": {
								"schema": {
									"allOf": [
										{
											"$ref": "#/components/schemas/Category"
										}
									],
									"nullable": true
								}
							}
						}
					}
				},
				"tags": [
					"Category"
				],
				"security": [
					{
						"jwt": []
					}
				],
				"parameters": [
					{
						"in": "path",
						"name": "id",
						"required": true,
						"schema": {
							"type": "string"
						}
					}
				],
				"requestBody": {
					"required": true,
					"content": {
						"application/json": {
							"schema": {
								"$ref": "#/components/schemas/ICategoryPayload"
							}
						}
					}
				}
			},
			"delete": {
				"operationId": "DeleteCategory",
				"responses": {
					"200": {
						"description": "Ok",
						"content": {
							"application/json": {
								"schema": {
									"allOf": [
										{
											"$ref": "#/components/schemas/Category"
										}
									],
									"nullable": true
								}
							}
						}
					}
				},
				"tags": [
					"Category"
				],
				"security": [
					{
						"jwt": []
					}
				],
				"parameters": [
					{
						"in": "path",
						"name": "id",
						"required": true,
						"schema": {
							"type": "string"
						}
					}
				]
			}
		},
		"/api/v1/tracks": {
			"get": {
				"operationId": "GetTracks",
				"responses": {
					"200": {
						"description": "Ok",
						"content": {
							"application/json": {
								"schema": {
									"items": {
										"$ref": "#/components/schemas/Track"
									},
									"type": "array"
								}
							}
						}
					}
				},
				"tags": [
					"Track"
				],
				"security": [],
				"parameters": [
					{
						"in": "query",
						"name": "skip",
						"required": true,
						"schema": {
							"type": "string"
						}
					},
					{
						"in": "query",
						"name": "limit",
						"required": true,
						"schema": {
							"type": "string"
						}
					},
					{
						"in": "query",
						"name": "publisher",
						"required": true,
						"schema": {
							"type": "string"
						}
					},
					{
						"in": "query",
						"name": "title",
						"required": true,
						"schema": {
							"type": "string"
						}
					},
					{
						"in": "query",
						"name": "bpmlow",
						"required": true,
						"schema": {
							"type": "string"
						}
					},
					{
						"in": "query",
						"name": "bpmhigh",
						"required": true,
						"schema": {
							"type": "string"
						}
					},
					{
						"in": "query",
						"name": "key",
						"required": true,
						"schema": {
							"type": "string"
						}
					},
					{
						"in": "query",
						"name": "genre",
						"required": true,
						"schema": {
							"type": "string"
						}
					},
					{
						"in": "query",
						"name": "label",
						"required": true,
						"schema": {
							"type": "string"
						}
					},
					{
						"in": "query",
						"name": "artist",
						"required": true,
						"schema": {
							"type": "string"
						}
					}
				]
			},
			"post": {
				"operationId": "CreateTrack",
				"responses": {
					"200": {
						"description": "Ok",
						"content": {
							"application/json": {
								"schema": {
									"$ref": "#/components/schemas/Track"
								}
							}
						}
					}
				},
				"tags": [
					"Track"
				],
				"security": [],
				"parameters": [],
				"requestBody": {
					"required": true,
					"content": {
						"application/json": {
							"schema": {
								"$ref": "#/components/schemas/ITrackPayload"
							}
						}
					}
				}
			}
		},
		"/api/v1/tracks/search": {
			"get": {
				"operationId": "GetSearchTracks",
				"responses": {
					"200": {
						"description": "Ok",
						"content": {
							"application/json": {
								"schema": {
									"items": {
										"$ref": "#/components/schemas/Track"
									},
									"type": "array"
								}
							}
						}
					}
				},
				"tags": [
					"Track"
				],
				"security": [],
				"parameters": [
					{
						"in": "query",
						"name": "keyword",
						"required": true,
						"schema": {
							"type": "string"
						}
					},
					{
						"in": "query",
						"name": "skip",
						"required": true,
						"schema": {
							"type": "string"
						}
					},
					{
						"in": "query",
						"name": "limit",
						"required": true,
						"schema": {
							"type": "string"
						}
					}
				]
			}
		},
		"/api/v1/tracks/genre-tracks/{slug}": {
			"get": {
				"operationId": "GetGenreTracks",
				"responses": {
					"200": {
						"description": "Ok",
						"content": {
							"application/json": {
								"schema": {
									"items": {
										"$ref": "#/components/schemas/Track"
									},
									"type": "array"
								}
							}
						}
					}
				},
				"tags": [
					"Track"
				],
				"security": [],
				"parameters": [
					{
						"in": "path",
						"name": "slug",
						"required": true,
						"schema": {
							"type": "string"
						}
					},
					{
						"in": "query",
						"name": "skip",
						"required": true,
						"schema": {
							"type": "string"
						}
					},
					{
						"in": "query",
						"name": "limit",
						"required": true,
						"schema": {
							"type": "string"
						}
					}
				]
			}
		},
		"/api/v1/tracks/uploadBulk": {
			"post": {
				"operationId": "UploadBulk",
				"responses": {
					"200": {
						"description": "Ok",
						"content": {
							"application/json": {
								"schema": {
									"$ref": "#/components/schemas/Track"
								}
							}
						}
					}
				},
				"tags": [
					"Track"
				],
				"security": [],
				"parameters": [],
				"requestBody": {
					"required": true,
					"content": {
						"application/json": {
							"schema": {
								"$ref": "#/components/schemas/IUploadBulkPayload"
							}
						}
					}
				}
			}
		},
		"/api/v1/tracks/{slug}": {
			"get": {
				"operationId": "GetTrack",
				"responses": {
					"200": {
						"description": "Ok",
						"content": {
							"application/json": {
								"schema": {
									"allOf": [
										{
											"$ref": "#/components/schemas/Track"
										}
									],
									"nullable": true
								}
							}
						}
					}
				},
				"tags": [
					"Track"
				],
				"security": [],
				"parameters": [
					{
						"in": "path",
						"name": "slug",
						"required": true,
						"schema": {
							"type": "string"
						}
					}
				]
			}
		},
		"/api/v1/tracks/{id}": {
			"put": {
				"operationId": "UpdateTrack",
				"responses": {
					"200": {
						"description": "Ok",
						"content": {
							"application/json": {
								"schema": {
									"allOf": [
										{
											"$ref": "#/components/schemas/Track"
										}
									],
									"nullable": true
								}
							}
						}
					}
				},
				"tags": [
					"Track"
				],
				"security": [],
				"parameters": [
					{
						"in": "path",
						"name": "id",
						"required": true,
						"schema": {
							"type": "string"
						}
					}
				],
				"requestBody": {
					"required": true,
					"content": {
						"application/json": {
							"schema": {
								"$ref": "#/components/schemas/ITrackPayload"
							}
						}
					}
				}
			},
			"delete": {
				"operationId": "DeleteTrack",
				"responses": {
					"200": {
						"description": "Ok",
						"content": {
							"application/json": {
								"schema": {
									"allOf": [
										{
											"$ref": "#/components/schemas/Track"
										}
									],
									"nullable": true
								}
							}
						}
					}
				},
				"tags": [
					"Track"
				],
				"security": [],
				"parameters": [
					{
						"in": "path",
						"name": "id",
						"required": true,
						"schema": {
							"type": "string"
						}
					}
				]
			}
		},
		"/api/v1/keys": {
			"get": {
				"operationId": "GetKeys",
				"responses": {
					"200": {
						"description": "Ok",
						"content": {
							"application/json": {
								"schema": {
									"items": {
										"$ref": "#/components/schemas/Key"
									},
									"type": "array"
								}
							}
						}
					}
				},
				"tags": [
					"Key"
				],
				"security": [
					{
						"jwt": []
					}
				],
				"parameters": []
			},
			"post": {
				"operationId": "CreateKey",
				"responses": {
					"200": {
						"description": "Ok",
						"content": {
							"application/json": {
								"schema": {
									"$ref": "#/components/schemas/Key"
								}
							}
						}
					}
				},
				"tags": [
					"Key"
				],
				"security": [
					{
						"jwt": []
					}
				],
				"parameters": [],
				"requestBody": {
					"required": true,
					"content": {
						"application/json": {
							"schema": {
								"$ref": "#/components/schemas/IKeyPayload"
							}
						}
					}
				}
			}
		},
		"/api/v1/keys/{id}": {
			"get": {
				"operationId": "GetKey",
				"responses": {
					"200": {
						"description": "Ok",
						"content": {
							"application/json": {
								"schema": {
									"allOf": [
										{
											"$ref": "#/components/schemas/Key"
										}
									],
									"nullable": true
								}
							}
						}
					}
				},
				"tags": [
					"Key"
				],
				"security": [
					{
						"jwt": []
					}
				],
				"parameters": [
					{
						"in": "path",
						"name": "id",
						"required": true,
						"schema": {
							"type": "string"
						}
					}
				]
			},
			"put": {
				"operationId": "UpdateKey",
				"responses": {
					"200": {
						"description": "Ok",
						"content": {
							"application/json": {
								"schema": {
									"allOf": [
										{
											"$ref": "#/components/schemas/Key"
										}
									],
									"nullable": true
								}
							}
						}
					}
				},
				"tags": [
					"Key"
				],
				"security": [
					{
						"jwt": []
					}
				],
				"parameters": [
					{
						"in": "path",
						"name": "id",
						"required": true,
						"schema": {
							"type": "string"
						}
					}
				],
				"requestBody": {
					"required": true,
					"content": {
						"application/json": {
							"schema": {
								"$ref": "#/components/schemas/IKeyPayload"
							}
						}
					}
				}
			},
			"delete": {
				"operationId": "DeleteKey",
				"responses": {
					"200": {
						"description": "Ok",
						"content": {
							"application/json": {
								"schema": {
									"allOf": [
										{
											"$ref": "#/components/schemas/Key"
										}
									],
									"nullable": true
								}
							}
						}
					}
				},
				"tags": [
					"Key"
				],
				"security": [
					{
						"jwt": []
					}
				],
				"parameters": [
					{
						"in": "path",
						"name": "id",
						"required": true,
						"schema": {
							"type": "string"
						}
					}
				]
			}
		}
	},
	"servers": [
		{
			"url": "/"
		}
	]
}